task_executor/__init__.py
task_executor/exec/__init__.py
task_executor/utypes/__init__.py
task_executor-0.1.0.dist-info/METADATA
task_executor-0.1.0.dist-info/WHEEL
task_executor-0.1.0.dist-info/RECORD
